car-parking-project/design.sv
// Code your design here
`timescale 1ns / 1ps
module parking_system(
	input clk,reset_n,
    input sensor_entrance,sensor_exit,
    input [1:0] password_1,password_2,
    output wire GREEN_LED,RED_LED,
    output reg [6:0] HEX_1, HEX_2 
);
  // FSM states
  parameter IDLE = 3'b000, 
          WAIT_PASSWORD = 3'b001, 
          WRONG_PASS = 3'b010, 
          RIGHT_PASS = 3'b011,
          STOP = 3'b100;
  // Moore FSM : output just depends on the current state
 reg[2:0] current_state, next_state;
 reg[31:0] counter_wait;
 reg red_tmp,green_tmp;
  
  // Next state
 always @(posedge clk or negedge reset_n)
 begin
 if(~reset_n) 
 current_state = IDLE;
 else
 current_state = next_state;
 end
  
   // counter_wait
 always @(posedge clk or negedge reset_n) 
 begin
 if(~reset_n) 
 counter_wait <= 0;
 else if(current_state==WAIT_PASSWORD)
 counter_wait <= counter_wait + 1;
 else 
 counter_wait <= 0;
 end
   // change state
 always @(*)
   begin
     case(current_state)
       
       IDLE: begin
         if(sensor_entrance==1)
           next_state=WAIT_PASSWORD;
         else
           next_state=IDLE;
       end
       
       WAIT_PASSWORD: begin
         if(counter_wait<=3)
           next_state=WAIT_PASSWORD;
         else
           begin
             if((password_1==2'b01)&&(password_2==2'b10))
               next_state=RIGHT_PASS;
             else
               next_state=WRONG_PASS;
           end
       end
       
        WRONG_PASS: begin
         if((password_1==2'b01)&&(password_2==2'b10))
               next_state=RIGHT_PASS;
             else
               next_state=WRONG_PASS;
        end
       
       RIGHT_PASS:begin
         if(sensor_entrance==1 && sensor_exit == 1)
           next_state=STOP;
         else if(sensor_exit==1)
           next_state=IDLE;
         else
           next_state=RIGHT_PASS;
       end
       
       STOP: begin
         if((password_1==2'b01)&&(password_2==2'b10))
           next_state=RIGHT_PASS;
         else
           next_state=STOP;
       end
       
       default: next_state = IDLE;
      
     endcase
   end
     
 // LEDs and output, change the period of blinking LEDs here
     always @(posedge clk)begin
       case(current_state)
         IDLE:begin
             green_tmp = 1'b0;
             red_tmp = 1'b0;
             HEX_1 = 7'b1111111; // off
             HEX_2 = 7'b1111111; // off
             end
         WAIT_PASSWORD: begin
             green_tmp = 1'b0;
             red_tmp = 1'b1;
             HEX_1 = 7'b000_0110; // E
             HEX_2 = 7'b010_1011; // n 
             end
		 WRONG_PASS: begin
             green_tmp = 1'b0;
             red_tmp = ~red_tmp;
             HEX_1 = 7'b000_0110; // E
             HEX_2 = 7'b000_0110; // E 
             end
 		RIGHT_PASS: begin
             green_tmp = ~green_tmp;
             red_tmp = 1'b0;
             HEX_1 = 7'b000_0010; // 6
             HEX_2 = 7'b100_0000; // 0 
             end
	 	STOP: begin
             green_tmp = 1'b0;
             red_tmp = ~red_tmp;
             HEX_1 = 7'b001_0010; // 5
             HEX_2 = 7'b000_1100; // P 
             end
       endcase
     end
  	assign RED_LED = red_tmp  ;
 	assign GREEN_LED = green_tmp;
      
endmodule

car-parking-project/testbench.sv
`timescale 1ns / 1ps
module tb_parking_system;

  // Inputs
  reg clk;
  reg reset_n;
  reg sensor_entrance;
  reg sensor_exit;
  reg [1:0] password_1;
  reg [1:0] password_2;

  // Outputs
  wire GREEN_LED;
  wire RED_LED;
  wire [6:0] HEX_1;
  wire [6:0] HEX_2;
  
  // Instantiate the Unit Under Test (UUT)
  parking_system uut (
  .clk(clk), 
  .reset_n(reset_n), 
  .sensor_entrance(sensor_entrance), 
  .sensor_exit(sensor_exit), 
  .password_1(password_1), 
  .password_2(password_2), 
  .GREEN_LED(GREEN_LED), 
  .RED_LED(RED_LED), 
  .HEX_1(HEX_1), 
 .HEX_2(HEX_2)
 );
  
 initial begin
 clk = 0;
 forever #10 clk = ~clk;
 end
  
 initial begin
   
  // VCD waveform commands
  $dumpfile("parking_system.vcd");
  $dumpvars(1, tb_parking_system);
   
 // Initialize Inputs
 reset_n = 0;
 sensor_entrance = 0;
 sensor_exit = 0;
 password_1 = 0;
 password_2 = 0;
 // Wait 100 ns for global reset to finish
 #100;
      reset_n = 1;
 #20;
 sensor_entrance = 1;
 #1000;
 sensor_entrance = 0;
 password_1 = 1;
 password_2 = 2;
 #2000;
 sensor_exit =1;
 #1000;
   

   
 $finish;      // End simulation
 
 end
      
endmodule

car-parking-project/parking_system.vcd
$date
	Thu Jun 26 12:40:09 2025
$end
$version
	Icarus Verilog
$end
$timescale
	1ps
$end
$scope module tb_parking_system $end
$var wire 1 ! RED_LED $end
$var wire 7 " HEX_2 [6:0] $end
$var wire 7 # HEX_1 [6:0] $end
$var wire 1 $ GREEN_LED $end
$var reg 1 % clk $end
$var reg 2 & password_1 [1:0] $end
$var reg 2 ' password_2 [1:0] $end
$var reg 1 ( reset_n $end
$var reg 1 ) sensor_entrance $end
$var reg 1 * sensor_exit $end
$upscope $end
$enddefinitions $end
$comment Show the parameter values. $end
$dumpall
$end
#0
$dumpvars
0*
0)
0(
b0 '
b0 &
0%
x$
bx #
bx "
x!
$end
#10000
b1111111 "
b1111111 #
0!
0$
1%
#20000
0%
#30000
1%
#40000
0%
#50000
1%
#60000
0%
#70000
1%
#80000
0%
#90000
1%
#100000
0%
1(
#110000
1%
#120000
0%
1)
#130000
b101011 "
b110 #
1!
1%
#140000
0%
#150000
1%
#160000
0%
#170000
1%
#180000
0%
#190000
1%
#200000
0%
#210000
b110 "
0!
1%
#220000
0%
#230000
1!
1%
#240000
0%
#250000
0!
1%
#260000
0%
#270000
1!
1%
#280000
0%
#290000
0!
1%
#300000
0%
#310000
1!
1%
#320000
0%
#330000
0!
1%
#340000
0%
#350000
1!
1%
#360000
0%
#370000
0!
1%
#380000
0%
#390000
1!
1%
#400000
0%
#410000
0!
1%
#420000
0%
#430000
1!
1%
#440000
0%
#450000
0!
1%
#460000
0%
#470000
1!
1%
#480000
0%
#490000
0!
1%
#500000
0%
#510000
1!
1%
#520000
0%
#530000
0!
1%
#540000
0%
#550000
1!
1%
#560000
0%
#570000
0!
1%
#580000
0%
#590000
1!
1%
#600000
0%
#610000
0!
1%
#620000
0%
#630000
1!
1%
#640000
0%
#650000
0!
1%
#660000
0%
#670000
1!
1%
#680000
0%
#690000
0!
1%
#700000
0%
#710000
1!
1%
#720000
0%
#730000
0!
1%
#740000
0%
#750000
1!
1%
#760000
0%
#770000
0!
1%
#780000
0%
#790000
1!
1%
#800000
0%
#810000
0!
1%
#820000
0%
#830000
1!
1%
#840000
0%
#850000
0!
1%
#860000
0%
#870000
1!
1%
#880000
0%
#890000
0!
1%
#900000
0%
#910000
1!
1%
#920000
0%
#930000
0!
1%
#940000
0%
#950000
1!
1%
#960000
0%
#970000
0!
1%
#980000
0%
#990000
1!
1%
#1000000
0%
#1010000
0!
1%
#1020000
0%
#1030000
1!
1%
#1040000
0%
#1050000
0!
1%
#1060000
0%
#1070000
1!
1%
#1080000
0%
#1090000
0!
1%
#1100000
0%
#1110000
1!
1%
#1120000
0%
b10 '
b1 &
0)
#1130000
b1000000 "
b10 #
0!
1$
1%
#1140000
0%
#1150000
0$
1%
#1160000
0%
#1170000
1$
1%
#1180000
0%
#1190000
0$
1%
#1200000
0%
#1210000
1$
1%
#1220000
0%
#1230000
0$
1%
#1240000
0%
#1250000
1$
1%
#1260000
0%
#1270000
0$
1%
#1280000
0%
#1290000
1$
1%
#1300000
0%
#1310000
0$
1%
#1320000
0%
#1330000
1$
1%
#1340000
0%
#1350000
0$
1%
#1360000
0%
#1370000
1$
1%
#1380000
0%
#1390000
0$
1%
#1400000
0%
#1410000
1$
1%
#1420000
0%
#1430000
0$
1%
#1440000
0%
#1450000
1$
1%
#1460000
0%
#1470000
0$
1%
#1480000
0%
#1490000
1$
1%
#1500000
0%
#1510000
0$
1%
#1520000
0%
#1530000
1$
1%
#1540000
0%
#1550000
0$
1%
#1560000
0%
#1570000
1$
1%
#1580000
0%
#1590000
0$
1%
#1600000
0%
#1610000
1$
1%
#1620000
0%
#1630000
0$
1%
#1640000
0%
#1650000
1$
1%
#1660000
0%
#1670000
0$
1%
#1680000
0%
#1690000
1$
1%
#1700000
0%
#1710000
0$
1%
#1720000
0%
#1730000
1$
1%
#1740000
0%
#1750000
0$
1%
#1760000
0%
#1770000
1$
1%
#1780000
0%
#1790000
0$
1%
#1800000
0%
#1810000
1$
1%
#1820000
0%
#1830000
0$
1%
#1840000
0%
#1850000
1$
1%
#1860000
0%
#1870000
0$
1%
#1880000
0%
#1890000
1$
1%
#1900000
0%
#1910000
0$
1%
#1920000
0%
#1930000
1$
1%
#1940000
0%
#1950000
0$
1%
#1960000
0%
#1970000
1$
1%
#1980000
0%
#1990000
0$
1%
#2000000
0%
#2010000
1$
1%
#2020000
0%
#2030000
0$
1%
#2040000
0%
#2050000
1$
1%
#2060000
0%
#2070000
0$
1%
#2080000
0%
#2090000
1$
1%
#2100000
0%
#2110000
0$
1%
#2120000
0%
#2130000
1$
1%
#2140000
0%
#2150000
0$
1%
#2160000
0%
#2170000
1$
1%
#2180000
0%
#2190000
0$
1%
#2200000
0%
#2210000
1$
1%
#2220000
0%
#2230000
0$
1%
#2240000
0%
#2250000
1$
1%
#2260000
0%
#2270000
0$
1%
#2280000
0%
#2290000
1$
1%
#2300000
0%
#2310000
0$
1%
#2320000
0%
#2330000
1$
1%
#2340000
0%
#2350000
0$
1%
#2360000
0%
#2370000
1$
1%
#2380000
0%
#2390000
0$
1%
#2400000
0%
#2410000
1$
1%
#2420000
0%
#2430000
0$
1%
#2440000
0%
#2450000
1$
1%
#2460000
0%
#2470000
0$
1%
#2480000
0%
#2490000
1$
1%
#2500000
0%
#2510000
0$
1%
#2520000
0%
#2530000
1$
1%
#2540000
0%
#2550000
0$
1%
#2560000
0%
#2570000
1$
1%
#2580000
0%
#2590000
0$
1%
#2600000
0%
#2610000
1$
1%
#2620000
0%
#2630000
0$
1%
#2640000
0%
#2650000
1$
1%
#2660000
0%
#2670000
0$
1%
#2680000
0%
#2690000
1$
1%
#2700000
0%
#2710000
0$
1%
#2720000
0%
#2730000
1$
1%
#2740000
0%
#2750000
0$
1%
#2760000
0%
#2770000
1$
1%
#2780000
0%
#2790000
0$
1%
#2800000
0%
#2810000
1$
1%
#2820000
0%
#2830000
0$
1%
#2840000
0%
#2850000
1$
1%
#2860000
0%
#2870000
0$
1%
#2880000
0%
#2890000
1$
1%
#2900000
0%
#2910000
0$
1%
#2920000
0%
#2930000
1$
1%
#2940000
0%
#2950000
0$
1%
#2960000
0%
#2970000
1$
1%
#2980000
0%
#2990000
0$
1%
#3000000
0%
#3010000
1$
1%
#3020000
0%
#3030000
0$
1%
#3040000
0%
#3050000
1$
1%
#3060000
0%
#3070000
0$
1%
#3080000
0%
#3090000
1$
1%
#3100000
0%
#3110000
0$
1%
#3120000
0%
1*
#3130000
b1111111 "
b1111111 #
1%
