full subtractor code/design.sv
// Code your design here
module full_subtractor( diff, borrow,a,b,c);
  input a,b,c;
  output diff, borrow;
  assign diff= (a^b^c);
  assign borrow= (~a&b)|(~(a^b)&c);
endmodule

full subtractor code/testbench.sv
// Code your testbench here

module testbench;
  reg a,b,c;
  wire diff, borrow;
  
  full_subtractor uut(diff,borrow,a,b,c);
  
  initial begin
    a=1'b0; b=1'b0; c=1'b0;
    #2 a=1'b0; b=1'b0; c=1'b1;
    #2 a=1'b0; b=1'b1; c=1'b0;
    #2 a=1'b0; b=1'b1; c=1'b1;
    #2 a=1'b1; b=1'b0; c=1'b0;
    #2 a=1'b1; b=1'b0; c=1'b1;
    #2 a=1'b1; b=1'b1; c=1'b0;
    #2 a=1'b1; b=1'b1; c=1'b1;
    #2 $finish;
  end
    
  initial begin
    $dumpfile("dump.vcd");
    $dumpvars(1,testbench);
  end
endmodule

full subtractor code/dump.vcd
$date
	Sat Jan  4 03:53:51 2025
$end
$version
	Icarus Verilog
$end
$timescale
	1s
$end
$scope module testbench $end
$var wire 1 ! diff $end
$var wire 1 " borrow $end
$var reg 1 # a $end
$var reg 1 $ b $end
$var reg 1 % c $end
$upscope $end
$enddefinitions $end
$comment Show the parameter values. $end
$dumpall
$end
#0
$dumpvars
0%
0$
0#
0"
0!
$end
#2
1"
1!
1%
#4
0%
1$
#6
0!
1%
#8
0"
1!
0%
0$
1#
#10
0!
1%
#12
0%
1$
#14
1"
1!
1%
