result/design.sv
// Code your design here
module full_adder(sum,carry,a,b,c);
  input a,b,c;
  output sum, carry;
  assign sum= a^b^c;
  assign carry= (a&b)|c&(a^b);
endmodule

result/testbench.sv
// Code your testbench here
module testbench;
  reg a,b,c;  // input
  wire sum, carry;  //output
 //instatize
  
  full_adder uut(sum, carry,a,b,c);
  
//   test cases
  
  initial begin
      #2 a=1'b0 ; b=1'b0; c=1'b0;
      #2 a=1'b0 ; b=1'b0; c=1'b1;
      #2 a=1'b0 ; b=1'b1; c=1'b0;
      #2 a=1'b0 ; b=1'b1; c=1'b1;
      #2 a=1'b1 ; b=1'b0; c=1'b0;
      #2 a=1'b1 ; b=1'b0; c=1'b1;
      #2 a=1'b1 ; b=1'b1; c=1'b0;
      #2 a=1'b1 ; b=1'b1; c=1'b1;
      #2 $finish;
  end
//  dumping the file to obtain graphs
  initial begin
    $dumpfile("full_adder.vcd");
    $dumpvars(1,testbench);
  end
endmodule

result/full_adder.vcd
$date
	Thu Jan  2 01:08:53 2025
$end
$version
	Icarus Verilog
$end
$timescale
	1s
$end
$scope module testbench $end
$var wire 1 ! sum $end
$var wire 1 " carry $end
$var reg 1 # a $end
$var reg 1 $ b $end
$var reg 1 % c $end
$upscope $end
$enddefinitions $end
$comment Show the parameter values. $end
$dumpall
$end
#0
$dumpvars
x%
x$
x#
x"
x!
$end
#2
0"
0!
0%
0$
0#
#4
1!
1%
#6
0%
1$
#8
1"
0!
1%
#10
0"
1!
0%
0$
1#
#12
1"
0!
1%
#14
0%
1$
#16
1!
1%
